{
  "TECHCORP": {
    "currentPrice": 834.45,
    "last10Prices": [
      847.96,
      862.83,
      854.26,
      826.57,
      846.2,
      818.93,
      833.73,
      835.98,
      795.58,
      834.45
    ],
    "maxmin": [
      1110,
      300
    ],
    "trend": "stable",
    "sector": "Technology",
    "marketCap": "1.5B",
    "volatility": 1,
    "CEO": "Alice Smith",
    "image": "techcorp"
  },
  "AUTOWORKS": {
    "currentPrice": 27.67,
    "last10Prices": [
      26.3,
      26.89,
      27.09,
      27.18,
      26.39,
      27.19,
      27.08,
      26.83,
      27.4,
      27.67
    ],
    "trend": "up",
    "maxmin": [
      90,
      20
    ],
    "sector": "Automotive",
    "marketCap": "850M",
    "volatility": 0.75,
    "CEO": "John Doe",
    "image": "autoworks"
  },
  "ECOENERGY": {
    "currentPrice": 866.21,
    "last10Prices": [
      871.36,
      840.67,
      849.89,
      841.96,
      835.37,
      814.83,
      847.38,
      813.87,
      845.87,
      866.21
    ],
    "maxmin": [
      1300,
      700
    ],
    "trend": "up",
    "sector": "Energy",
    "marketCap": "500M",
    "volatility": 0.8,
    "CEO": "Jane Doe",
    "image": "ecoenergy"
  },
  "FOODIE": {
    "currentPrice": 526.95,
    "last10Prices": [
      545.32,
      548.36,
      518.86,
      498.31,
      523.27,
      518.32,
      523.15,
      500.75,
      499.29,
      526.95
    ],
    "maxmin": [
      665,
      180
    ],
    "trend": "stable",
    "sector": "Food & Beverage",
    "marketCap": "300M",
    "volatility": 1.2,
    "CEO": "Emily Green",
    "image": "foodie"
  },
  "MEDICAL": {
    "currentPrice": 464.8,
    "last10Prices": [
      498.75,
      522.88,
      527.86,
      521.89,
      497.24,
      463.04,
      446.47,
      457.41,
      434.97,
      464.8
    ],
    "maxmin": [
      775,
      285
    ],
    "trend": "stable",
    "sector": "Healthcare",
    "marketCap": "2B",
    "volatility": 1.4,
    "CEO": "Michael Brown",
    "image": "medical"
  },
  "RETAILER": {
    "currentPrice": 57.63,
    "last10Prices": [
      59.47,
      59.81,
      59.82,
      61.38,
      59.75,
      60.63,
      58.19,
      59.16,
      56.74,
      57.63
    ],
    "maxmin": [
      190,
      55
    ],
    "trend": "stable",
    "sector": "Retail",
    "marketCap": "750M",
    "volatility": 0.9,
    "CEO": "Laura Wilson",
    "image": "retailer"
  },
  "FINTECH": {
    "currentPrice": 917.6,
    "last10Prices": [
      989.65,
      990.6,
      1017.84,
      963.42,
      995.47,
      994.99,
      975.5,
      928.59,
      916.69,
      917.6
    ],
    "maxmin": [
      1320,
      270
    ],
    "trend": "stable",
    "sector": "Finance",
    "marketCap": "1.8B",
    "volatility": 1.3,
    "CEO": "Chris Johnson",
    "image": "fintech"
  },
  "TRAVEL": {
    "currentPrice": 52.48,
    "last10Prices": [
      57.46,
      57.25,
      55.42,
      54.19,
      54.97,
      53.06,
      53.3,
      54.49,
      52.69,
      52.48
    ],
    "maxmin": [
      300,
      35
    ],
    "trend": "down",
    "sector": "Travel & Leisure",
    "marketCap": "400M",
    "volatility": 0.8,
    "CEO": "Sarah Lee",
    "image": "travel"
  },
  "EDUCATECH": {
    "currentPrice": 107.13,
    "last10Prices": [
      117.37,
      111.95,
      113.79,
      112.38,
      109.09,
      109.62,
      108.2,
      109.89,
      108.52,
      107.13
    ],
    "maxmin": [
      670,
      100
    ],
    "trend": "down",
    "sector": "Education",
    "marketCap": "600M",
    "volatility": 1.1,
    "CEO": "Thomas Moore",
    "image": "educatech"
  },
  "CLEANENERGY": {
    "currentPrice": 591.28,
    "last10Prices": [
      628.01,
      606.9,
      588.25,
      571.3,
      588.37,
      566.63,
      539.37,
      564.55,
      558.3,
      591.28
    ],
    "maxmin": [
      1600,
      500
    ],
    "trend": "stable",
    "sector": "Clean Energy",
    "marketCap": "500M",
    "volatility": 1.2,
    "CEO": "Karen White",
    "image": "cleanenergy"
  },
  "BIOGENICS": {
    "currentPrice": 288.97,
    "last10Prices": [
      295.89,
      287.1,
      277.97,
      263.86,
      267.11,
      278.26,
      270.97,
      274.53,
      288.01,
      288.97
    ],
    "maxmin": [
      550,
      200
    ],
    "trend": "up",
    "sector": "Biotechnology",
    "marketCap": "1.2B",
    "volatility": 1.1,
    "CEO": "Anna Russell",
    "image": "biogenics"
  },
  "AEROSPACE": {
    "currentPrice": 548.73,
    "last10Prices": [
      550.83,
      554.58,
      578.4,
      599.63,
      634.38,
      606.1,
      589.84,
      554.49,
      549.74,
      548.73
    ],
    "maxmin": [
      900,
      430
    ],
    "trend": "down",
    "sector": "Aerospace & Defense",
    "marketCap": "2B",
    "volatility": 1.3,
    "CEO": "Robert King",
    "image": "aerospace"
  },
  "CYBERPROTECT": {
    "currentPrice": 155.61,
    "last10Prices": [
      147.28,
      148.4,
      150.91,
      145.64,
      151.52,
      154.01,
      154.98,
      156.35,
      149.44,
      155.61
    ],
    "maxmin": [
      300,
      120
    ],
    "trend": "stable",
    "sector": "Cybersecurity",
    "marketCap": "750M",
    "volatility": 1,
    "CEO": "Samantha Richards",
    "image": "cyberprotect"
  },
  "GREENSCAPE": {
    "currentPrice": 38.36,
    "last10Prices": [
      38.59,
      39.1,
      39.78,
      38.66,
      38.76,
      39.77,
      40.94,
      39.69,
      39.17,
      38.36
    ],
    "maxmin": [
      95,
      30
    ],
    "trend": "down",
    "sector": "Agriculture",
    "marketCap": "300M",
    "volatility": 0.7,
    "CEO": "Matthew Ellis",
    "image": "greenscape"
  },
  "WATERWORKS": {
    "currentPrice": 87.96,
    "last10Prices": [
      80.63,
      82.63,
      81.19,
      82.95,
      82.67,
      83.37,
      84.48,
      86.97,
      85.84,
      87.96
    ],
    "maxmin": [
      120,
      50
    ],
    "trend": "stable",
    "sector": "Utilities",
    "marketCap": "450M",
    "volatility": 0.6,
    "CEO": "Ethan Wallace",
    "image": "waterworks"
  },
  "NEWMEDIA": {
    "currentPrice": 133.85,
    "last10Prices": [
      123,
      126.13,
      125.77,
      125.75,
      122.95,
      129.06,
      125.63,
      127.48,
      128.17,
      133.85
    ],
    "maxmin": [
      220,
      90
    ],
    "trend": "up",
    "sector": "Media",
    "marketCap": "1.1B",
    "volatility": 1,
    "CEO": "Mark Foster",
    "image": "newmedia"
  },
  "GLOBALTRADE": {
    "currentPrice": 123.12,
    "last10Prices": [
      109.31,
      112.91,
      110.42,
      112.95,
      112.91,
      115.91,
      116.91,
      120.04,
      124.57,
      123.12
    ],
    "maxmin": [
      150,
      50
    ],
    "trend": "stable",
    "sector": "Logistics",
    "marketCap": "650M",
    "volatility": 0.8,
    "CEO": "Daniel Kim",
    "image": "globaltrade"
  }
}